CS 233/Lab1/blackbox.v
module blackbox(w, x, l, b);
    output w;
    input  x, l, b;
    wire   w02, w03, w05, w06, w11, w16, w17, w20, w28, w32, w33, w35, w38, w71, w79, w87, w89, w91;
    and a39(w, w03, w06);
    or  o59(w03, w02, w05);
    and a19(w02, w11, w87);
    and a55(w05, w11, w89);
    not n68(w89, w87);
    or  o94(w06, w71, w32);
    not n84(w71, w32);
    and a18(w32, w91, w16);
    not n99(w91, l);
    or  o44(w16, w17, w33);
    not n60(w17, b);
    and a80(w33, x, w38);
    not n37(w38, x);
    or  o12(w87, w28, x, w79);
    not n53(w28, b);
    not n36(w79, l);
    or  o8(w11, b, w35, w20);
    not n47(w35, l);
    not n82(w20, x);
endmodule // blackbox

CS 233/Lab1/blackbox_tb.v
module blackbox_test;

    reg x, l, b;                           // these are inputs to "circuit under test"
                                          // use "reg" not "wire" so can assign a value
    wire w;                        // wires for the outputs of "circuit under test"

    blackbox box(w, x, l, b);  // the circuit under test

    initial begin                             // initial = run at beginning of simulation
                                          // begin/end = associate block with initial

        $dumpfile("blackbox_test.vcd");                  // name of dump file to create
        $dumpvars(0,blackbox_test);                 // record all signals of module "sc_test" and sub-modules
                                          // remember to change "sc_test" to the correct
                                          // module name when writing your own test benches

        // test all four input combinations
        // remember that 2 inputs means 2^2 = 4 combinations
        // 3 inputs would mean 2^3 = 8 combinations to test, and so on
        // this is very similar to the input columns of a truth table
        x = 0; l = 0; b = 0; # 10;             // set initial values and wait 10 time units
        x = 0; l = 0; b = 1; # 10;             // set initial values and wait 10 time units
        x = 0; l = 1; b = 0; # 10;             // set initial values and wait 10 time units
        x = 0; l = 1; b = 1; # 10;             // set initial values and wait 10 time units
        x = 1; l = 0; b = 0; # 10;             // set initial values and wait 10 time units
        x = 1; l = 0; b = 1; # 10;             // set initial values and wait 10 time units
        x = 1; l = 1; b = 0; # 10;             // set initial values and wait 10 time units
        x = 1; l = 1; b = 1; # 10;             // set initial values and wait 10 time units

        $finish;                              // end the simulation
    end

    initial
    $monitor("At time %2t, x = %d l = %d b = %d w = %d",
             $time, x, l, b, w);
endmodule //

CS 233 - Computer Architecture/Lab1/blackbox_test.vcd
$date
	Sun Sep  2 15:54:45 2018
$end
$version
	Icarus Verilog
$end
$timescale
	1s
$end
$scope module blackbox_test $end
$var wire 1 ! w $end
$var reg 1 " b $end
$var reg 1 # l $end
$var reg 1 $ x $end
$scope module box $end
$var wire 1 " b $end
$var wire 1 # l $end
$var wire 1 ! w $end
$var wire 1 % w02 $end
$var wire 1 & w03 $end
$var wire 1 ' w05 $end
$var wire 1 ( w06 $end
$var wire 1 ) w11 $end
$var wire 1 * w16 $end
$var wire 1 + w17 $end
$var wire 1 , w20 $end
$var wire 1 - w28 $end
$var wire 1 . w32 $end
$var wire 1 / w33 $end
$var wire 1 0 w35 $end
$var wire 1 1 w38 $end
$var wire 1 2 w71 $end
$var wire 1 3 w79 $end
$var wire 1 4 w87 $end
$var wire 1 5 w89 $end
$var wire 1 6 w91 $end
$var wire 1 $ x $end
$upscope $end
$upscope $end
$enddefinitions $end
#0
$dumpvars
16
05
14
13
02
11
10
0/
1.
1-
1,
1+
1*
1)
1(
0'
1&
1%
0$
0#
0"
1!
$end
#10
1!
12
1(
0.
0*
0+
0-
1"
#20
1*
1+
1-
06
03
00
0"
1#
#30
1!
1'
1&
15
0%
0*
04
0+
0-
1"
#40
02
1.
0'
1*
05
1%
1+
1-
16
13
10
01
14
0,
0"
0#
1$
#50
1!
12
1(
0.
0*
0+
0-
1"
#60
0!
0&
1*
0%
1+
1-
0)
06
03
00
0"
1#
#70
1!
1&
0*
1%
0+
0-
1)
1"
