CS 233 - Computer Architecture/Lab1/sc_block.v
module sc_block(s, c, a, b);
    output s, c;
    input  a, b;
    wire   w1, w2, not_a, not_b;

    // the "c" output is just the AND of the two inputs
    and a1(c, a, b);

    // the "s" output is 1 only when exactly one of the inputs is 1
    not n1(not_a, a);
    not n2(not_b, b);
    and a2(w1, a, not_b);
    and a3(w2, b, not_a);
    or  o1(s, w1, w2);
endmodule // sc_blocky

CS 233/Lab1/sc2_block.v
// Complete the sc2_block module in this file
// Don't put any code in this file besides the sc2_block

module sc2_block(s, cout, a, b, cin);
	 input a,b, cin;
	 output s, cout;
	 wire w1,w2,w3;
	 sc_block t1(w1,w2,a,b);
	 sc_block t2(s,w3,w1,cin);
	 or o1(cout,w3,w2);
endmodule // sc2_blockyy

CS 233/Lab1/sc2_block_tb.v
module sc2_test;

    reg a_in, b_in, cin_in;                           // these are inputs to "circuit under test"
                                          // use "reg" not "wire" so can assign a value
    wire s, c_out;                        // wires for the outputs of "circuit under test"

    sc2_block sc2(s, c_out, a_in, b_in, cin_in);  // the circuit under test

    initial begin                             // initial = run at beginning of simulation
                                          // begin/end = associate block with initial

        $dumpfile("sc2.vcd");                  // name of dump file to create
        $dumpvars(0,sc2_test);                 // record all signals of module "sc_test" and sub-modules
                                          // remember to change "sc_test" to the correct
                                          // module name when writing your own test benches

        // test all four input combinations
        // remember that 2 inputs means 2^2 = 4 combinations
        // 3 inputs would mean 2^3 = 8 combinations to test, and so on
        // this is very similar to the input columns of a truth table
        a_in = 0; b_in = 0; cin_in = 0; # 10;             // set initial values and wait 10 time units
        a_in = 0; b_in = 0; cin_in = 1; # 10;             // set initial values and wait 10 time units
        a_in = 0; b_in = 1; cin_in = 0; # 10;             // set initial values and wait 10 time units
        a_in = 0; b_in = 1; cin_in = 1; # 10;             // set initial values and wait 10 time units
        a_in = 1; b_in = 0; cin_in = 0; # 10;             // set initial values and wait 10 time units
        a_in = 1; b_in = 0; cin_in = 1; # 10;             // set initial values and wait 10 time units
        a_in = 1; b_in = 1; cin_in = 0; # 10;             // set initial values and wait 10 time units
        a_in = 1; b_in = 1; cin_in = 1; # 10;             // set initial values and wait 10 time units

        $finish;                              // end the simulation
    end

    initial
    $monitor("At time %2t, a_in = %d b_in = %d s = %d c_out = %d cin_in = %d",
             $time, a_in, b_in, s, c_out, cin_in);
endmodule // sc2_testyy

CS 233 - Computer Architecture/Lab1/sc2.vcd
$date
	Thu Aug 30 14:39:55 2018
$end
$version
	Icarus Verilog
$end
$timescale
	1s
$end
$scope module sc2_test $end
$var wire 1 ! s $end
$var wire 1 " c_out $end
$var reg 1 # a_in $end
$var reg 1 $ b_in $end
$var reg 1 % cin_in $end
$scope module sc2 $end
$var wire 1 # a $end
$var wire 1 $ b $end
$var wire 1 % cin $end
$var wire 1 " cout $end
$var wire 1 & w3 $end
$var wire 1 ' w2 $end
$var wire 1 ( w1 $end
$var wire 1 ! s $end
$scope module t1 $end
$var wire 1 # a $end
$var wire 1 $ b $end
$var wire 1 ' c $end
$var wire 1 ) not_a $end
$var wire 1 * not_b $end
$var wire 1 ( s $end
$var wire 1 + w1 $end
$var wire 1 , w2 $end
$upscope $end
$scope module t2 $end
$var wire 1 ( a $end
$var wire 1 % b $end
$var wire 1 & c $end
$var wire 1 - not_a $end
$var wire 1 . not_b $end
$var wire 1 ! s $end
$var wire 1 / w1 $end
$var wire 1 0 w2 $end
$upscope $end
$upscope $end
$upscope $end
$enddefinitions $end
#0
$dumpvars
00
0/
1.
1-
0,
0+
1*
1)
0(
0'
0&
0%
0$
0#
0"
0!
$end
#10
1!
0.
10
1%
#20
0-
1/
1!
1(
1.
00
0*
1,
0%
1$
#30
0!
1"
0/
1&
0.
1%
#40
1!
1/
0-
0"
1+
1(
0&
1.
1*
0,
0)
0%
0$
1#
#50
0!
1"
0/
1&
0.
1%
#60
1-
0!
0(
0/
0+
0&
1.
1'
0*
0%
1$
#70
1!
0.
10
1%
